{
  "property": [
    {
      "model": "main.student",
      "pk": 1,
      "fields": {
        "first_name": "Петр",
        "last_name": "Петров",
        "avatar": "",
        "is_active": true
      }
    },
    {
      "model": "main.student",
      "pk": 2,
      "fields": {
        "first_name": "Семен",
        "last_name": "Семенов",
        "avatar": "",
        "is_active": false
      }
    },
    {
      "model": "main.student",
      "pk": 3,
      "fields": {
        "first_name": "Oleg",
        "last_name": "Maslov",
        "avatar": "",
        "is_active": true
      }
    },
    {
      "model": "main.student",
      "pk": 4,
      "fields": {
        "first_name": "Ivan",
        "last_name": "Petrov",
        "avatar": "",
        "is_active": true
      }
    }
  ]
}